<Properties StartupConfiguration="{19B42475-E101-2F62-42E3-A857D06F553C}|">
  <MonoDevelop.Ide.Workbench ActiveDocument="Assets/Script/FadeZone.cs">
    <Files>
      <File FileName="Assets/Script/PlayerController.cs" Line="134" Column="57" />
      <File FileName="Assets/climbZone.cs" Line="1" Column="1" />
      <File FileName="Assets/Script/FadeZone.cs" Line="27" Column="6" />
    </Files>
  </MonoDevelop.Ide.Workbench>
  <MonoDevelop.Ide.DebuggingService.PinnedWatches />
  <MonoDevelop.Ide.Workspace ActiveConfiguration="Debug" />
  <MonoDevelop.Ide.ItemProperties.Assembly-CSharp PreferredExecutionTarget="bef57843-800a-4454-9279-578b61e8cd11" />
  <MonoDevelop.Ide.DebuggingService.Breakpoints>
    <BreakpointStore />
  </MonoDevelop.Ide.DebuggingService.Breakpoints>
  <MultiItemStartupConfigurations />
</Properties>